gulper/__init__.py
gulper/cli.py
gulper/command/__init__.py
gulper/command/backup.py
gulper/command/cron.py
gulper/command/event.py
gulper/command/restore.py
gulper/core/__init__.py
gulper/core/backup.py
gulper/core/cron.py
gulper/core/event.py
gulper/core/restore.py
gulper/exception/__init__.py
gulper/exception/backup_not_found.py
gulper/exception/file_not_found.py
gulper/exception/operation_failed.py
gulper/module/__init__.py
gulper/module/config.py
gulper/module/database.py
gulper/module/dbs.py
gulper/module/file_system.py
gulper/module/logger.py
gulper/module/mysql.py
gulper/module/output.py
gulper/module/postgresql.py
gulper/module/schedule.py
gulper/module/sqlite.py
gulper/module/state.py
gulper/module/storage.py
gulper-0.0.15.dist-info/licenses/LICENSE.txt
gulper-0.0.15.dist-info/METADATA
gulper-0.0.15.dist-info/WHEEL
gulper-0.0.15.dist-info/entry_points.txt
gulper-0.0.15.dist-info/top_level.txt
gulper-0.0.15.dist-info/RECORD
